rfpimp.py
setup.cfg
setup.py
rfpimp.egg-info/PKG-INFO
rfpimp.egg-info/SOURCES.txt
rfpimp.egg-info/dependency_links.txt
rfpimp.egg-info/requires.txt
rfpimp.egg-info/top_level.txt