Metadata-Version: 2.1
Name: rfpimp
Version: 1.3.6
Summary: Permutation and drop-column importance for scikit-learn random forests and other models
Home-page: https://github.com/parrt/random-forest-importances
Author: Terence Parr, Kerem Turgutlu
Author-email: parrt@antlr.org, kcturgutlu@dons.usfca.edu
License: MIT
Keywords: scikit-learn random forest feature permutation importances
Platform: UNKNOWN
Classifier: License :: OSI Approved :: MIT License
Classifier: Intended Audience :: Developers
Requires-Python: >=3.6
